xdp_test_harness/__init__.py
xdp_test_harness/bptr_probe_counter.c
xdp_test_harness/client.py
xdp_test_harness/context.py
xdp_test_harness/default_config.py
xdp_test_harness/runner.py
xdp_test_harness/server.py
xdp_test_harness/utils.py
xdp_test_harness/virtual_config.py
xdp_test_harness/virtual_setup.py
xdp_test_harness/xdp_case.py
xdp_test_harness-0.1.4.dist-info/LICENSE
xdp_test_harness-0.1.4.dist-info/METADATA
xdp_test_harness-0.1.4.dist-info/WHEEL
xdp_test_harness-0.1.4.dist-info/top_level.txt
xdp_test_harness-0.1.4.dist-info/RECORD
