Metadata-Version: 2.1
Name: xdp-test-harness
Version: 0.1.4
Summary: Test harness for testing XDP programs.
Home-page: https://github.com/shoracek/xdp-test-harness
Author: Štěpán Horáček
Author-email: shoracek@redhat.com
License: UNKNOWN
Platform: UNKNOWN
Classifier: License :: OSI Approved :: GNU General Public License v3 (GPLv3)
Classifier: Topic :: Software Development :: Testing
Classifier: Topic :: System :: Networking
Classifier: Operating System :: POSIX :: Linux
Requires-Python: >= 3.5
Requires-Dist: pyroute2
Requires-Dist: scapy
